hylog/__init__.py
hylog/config.py
hylog/config.toml
hylog/formatters.py
hylog/handlers.py
hylog/logger.py
hylog/main.py
hylog/py.typed
hylog-0.1.8.dist-info/METADATA
hylog-0.1.8.dist-info/WHEEL
hylog-0.1.8.dist-info/RECORD
