Metadata-Version: 2.4
Name: hylog
Version: 0.1.8
Summary: Python logging utility
Author-email: ckbuhl <ckbuhl@gmail.com>
Requires-Python: >=3.10
